documents_to_markdown/__init__.py
documents_to_markdown/api.py
documents_to_markdown/cli.py
documents_to_markdown/config.py
documents_to_markdown/setup_wizard.py
documents_to_markdown/services/__init__.py
documents_to_markdown/services/base_converter.py
documents_to_markdown/services/document_converter_manager.py
documents_to_markdown/services/excel_converter.py
documents_to_markdown/services/image_converter.py
documents_to_markdown/services/pdf_converter.py
documents_to_markdown/services/plain_text_converter.py
documents_to_markdown/services/text_chunking_utils.py
documents_to_markdown/services/word_converter.py
documents_to_markdown/services/ai_services/__init__.py
documents_to_markdown/services/ai_services/ai_service_factory.py
documents_to_markdown/services/ai_services/base_ai_service.py
documents_to_markdown/services/ai_services/ollama_service.py
documents_to_markdown/services/ai_services/openai_service.py
documents_to_markdown-1.0.0.dist-info/licenses/LICENSE
documents_to_markdown-1.0.0.dist-info/METADATA
documents_to_markdown-1.0.0.dist-info/WHEEL
documents_to_markdown-1.0.0.dist-info/entry_points.txt
documents_to_markdown-1.0.0.dist-info/top_level.txt
documents_to_markdown-1.0.0.dist-info/RECORD
