Metadata-Version: 2.4
Name: documents-to-markdown
Version: 1.0.0
Summary: A comprehensive Python library for converting various document types to Markdown format
Home-page: https://github.com/ChaosAIs/DocumentsToMarkdown
Author: Felix
Author-email: Felix <yangzhenwu@gmail.com>
Maintainer-email: Felix <yangzhenwu@gmail.com>
License-Expression: MIT
Project-URL: Homepage, https://github.com/ChaosAIs/DocumentsToMarkdown
Project-URL: Repository, https://github.com/ChaosAIs/DocumentsToMarkdown.git
Project-URL: Documentation, https://github.com/ChaosAIs/DocumentsToMarkdown/blob/main/README.md
Project-URL: Bug Reports, https://github.com/ChaosAIs/DocumentsToMarkdown/issues
Keywords: document,conversion,markdown,word,pdf,excel,image,text,converter
Classifier: Development Status :: 4 - Beta
Classifier: Intended Audience :: Developers
Classifier: Operating System :: OS Independent
Classifier: Programming Language :: Python :: 3
Classifier: Programming Language :: Python :: 3.8
Classifier: Programming Language :: Python :: 3.9
Classifier: Programming Language :: Python :: 3.10
Classifier: Programming Language :: Python :: 3.11
Classifier: Programming Language :: Python :: 3.12
Classifier: Topic :: Software Development :: Libraries :: Python Modules
Classifier: Topic :: Text Processing :: Markup
Classifier: Topic :: Office/Business :: Office Suites
Requires-Python: >=3.8
License-File: LICENSE
Requires-Dist: python-docx>=1.2.0
Requires-Dist: PyMuPDF>=1.24.14
Requires-Dist: openpyxl>=3.1.2
Requires-Dist: xlrd>=2.0.1
Requires-Dist: python-dotenv>=1.0.0
Requires-Dist: openai>=1.51.0
Requires-Dist: Pillow>=10.4.0
Requires-Dist: requests>=2.32.3
Provides-Extra: dev
Requires-Dist: pytest>=6.0; extra == "dev"
Requires-Dist: pytest-cov>=2.0; extra == "dev"
Requires-Dist: black>=21.0; extra == "dev"
Requires-Dist: flake8>=3.8; extra == "dev"
Dynamic: author
Dynamic: home-page
Dynamic: license-file
Dynamic: requires-python
